telx/__init__.py
telx/base.py
telx-0.0.1.dist-info/METADATA
telx-0.0.1.dist-info/WHEEL
telx-0.0.1.dist-info/top_level.txt
telx-0.0.1.dist-info/RECORD
