Metadata-Version: 2.1
Name: telx
Version: 0.0.1
Summary: telegram bot api framework
Author: NuoQTe
Author-email: nuoqte@gmail.com
License: MIT
